django_event_observer/__init__.py
django_event_observer/apps.py
django_event_observer/event_manager.py
django_event_observer/config/__init__.py
django_event_observer/config/default_config.py
django_event_observer/events/__init__.py
django_event_observer/events/base.py
django_event_observer/events/models/__init__.py
django_event_observer/events/models/model_event_enums.py
django_event_observer/events/models/signal_event.py
django_event_observer/observers/__init__.py
django_event_observer/observers/abstract/__init__.py
django_event_observer/observers/abstract/base.py
django_event_observer-2024.11.8.dist-info/LICENSE
django_event_observer-2024.11.8.dist-info/METADATA
django_event_observer-2024.11.8.dist-info/WHEEL
django_event_observer-2024.11.8.dist-info/top_level.txt
django_event_observer-2024.11.8.dist-info/RECORD
