Metadata-Version: 2.1
Name: django_event_observer
Version: 2024.11.8
Author-email: "Sergei (Gefest) Romanchuk" <pod.cargoes.0u@icloud.com>
License: MIT License
Project-URL: homepage, https://github.com/GefMar/django_event_observer
Classifier: License :: OSI Approved :: MIT License
Requires-Python: >=3.8
License-File: LICENSE
Requires-Dist: django>=4.1
